mkdocs_include/__init__.py
mkdocs_include/plugin.py
mkdocs_include-1.0.0.dist-info/LICENSE
mkdocs_include-1.0.0.dist-info/METADATA
mkdocs_include-1.0.0.dist-info/WHEEL
mkdocs_include-1.0.0.dist-info/entry_points.txt
mkdocs_include-1.0.0.dist-info/top_level.txt
mkdocs_include-1.0.0.dist-info/RECORD
