Metadata-Version: 2.1
Name: mkdocs-include
Version: 1.0.0
Summary: A mkdocs plugin that lets you include files or trees.
Home-page: https://github.com/nqkdev/mkdocs-include
Author: Khanh Nguyen
Author-email: qknguyendev@gmail.com
License: Apache
Platform: UNKNOWN
License-File: LICENSE
Requires-Dist: mkdocs
